logfire_sdk.py
logfire_sdk-0.0.1.dist-info/METADATA
logfire_sdk-0.0.1.dist-info/WHEEL
logfire_sdk-0.0.1.dist-info/licenses/LICENSE
logfire_sdk-0.0.1.dist-info/RECORD
