Metadata-Version: 2.3
Name: logfire-sdk
Version: 0.0.1
Summary: Please use the `logfire` package instead.
Project-URL: Homepage, https://pypi.org/project/logfire/
Author-email: Pydantic Team <engineering@pydantic.dev>
License-Expression: MIT
License-File: LICENSE
Classifier: Development Status :: 1 - Planning
Classifier: Topic :: Internet
